xaal/__init__.py
xaal/zwave/__init__.py
xaal/zwave/__main__.py
xaal/zwave/cmdclass.py
xaal/zwave/core.py
xaal/zwave/debug.py
xaal/zwave/gw.py
xaal/zwave/test_gw.py
xaal/zwave/products/__init__.py
xaal/zwave/products/AeonLabs/DSB09104.py
xaal/zwave/products/AeonLabs/ZW096.py
xaal/zwave/products/AeonLabs/__init__.py
xaal/zwave/products/Aeotec/ZW100.py
xaal/zwave/products/Aeotec/__init__.py
xaal/zwave/products/Everspring/AD142.py
xaal/zwave/products/Everspring/__init__.py
xaal/zwave/products/Fibaro/FGWPE.py
xaal/zwave/products/Fibaro/__init__.py
xaal/zwave/products/GreenWave/PowerNode6.py
xaal/zwave/products/GreenWave/__init__.py
xaal/zwave/products/Zipato/RGBBulb.py
xaal/zwave/products/Zipato/__init__.py
xaal_zwave-0.2.2.dist-info/METADATA
xaal_zwave-0.2.2.dist-info/WHEEL
xaal_zwave-0.2.2.dist-info/top_level.txt
xaal_zwave-0.2.2.dist-info/RECORD
